{
  "scenario_id": "SC_1314",
  "condition": "C3",
  "condition_label": "Generic Learner",
  "seed": 17,
  "phase": "main",
  "model_id": "mock-model-v1",
  "temperature": 0.7,
  "prompt_version": "v1.0-mock",
  "generated_at": "2026-05-15T08:20:07.221232",
  "n_tutor_turns": 8,
  "n_learner_turns": 8,
  "exclusion_flag": false,
  "exclusion_code": "",
  "exclusion_reason": "",
  "total_input_tokens": 199,
  "total_output_tokens": 145,
  "system_prompt": "Act as a math student responding to the tutor.",
  "turns": [
    {
      "turn_index": 0,
      "tutor_turn": "(probing)If john is half the age of tanya, and she is 60, how old does that make him?",
      "learner_turn": "John is 60 x 2 = 120 years old.",
      "input_tokens": 27,
      "output_tokens": 9,
      "latency_ms": 748.6509458585933,
      "finish_reason": "stop",
      "mock": true
    },
    {
      "turn_index": 1,
      "tutor_turn": "(focus)he is half her age, not double. by x2 you are doubling.",
      "learner_turn": "Oh, I see. John is 60/2 = 30 years old.",
      "input_tokens": 21,
      "output_tokens": 10,
      "latency_ms": 446.9996746778608,
      "finish_reason": "stop",
      "mock": true
    },
    {
      "turn_index": 2,
      "tutor_turn": "(probing)now use this info to solve the problem again",
      "learner_turn": "The total age of John and Mary is 30 + 60 = 90 years old. The average age of John, Mary, and Tanya is (90 + 60)/3 = 60 y",
      "input_tokens": 18,
      "output_tokens": 30,
      "latency_ms": 423.0974924868477,
      "finish_reason": "stop",
      "mock": true
    },
    {
      "turn_index": 3,
      "tutor_turn": "(focus)you're right that you have 60 and 30, but you've forgotten to work out Mary's age. she is half of john's age, remember.",
      "learner_turn": "Oh, right. Mary is 30/2 = 15 years old. The total age of John and Mary is 30 + 15 = 45 years old. The average age of Joh",
      "input_tokens": 32,
      "output_tokens": 29,
      "latency_ms": 668.378780822645,
      "finish_reason": "stop",
      "mock": true
    },
    {
      "turn_index": 4,
      "tutor_turn": "(probing)you need to add the 3 ages together",
      "learner_turn": "The total age of John, Mary, and Tanya is 45 + 15 + 60 = 120 years old. The average age of John, Mary, and Tanya is 120/",
      "input_tokens": 17,
      "output_tokens": 28,
      "latency_ms": 562.4399443600239,
      "finish_reason": "stop",
      "mock": true
    },
    {
      "turn_index": 5,
      "tutor_turn": "(focus)you've told me that mary is 15, john is 30 and Tanya is 60. add these uo",
      "learner_turn": "The total age of John, Mary, and Tanya is 15 + 30 + 60 = 105 years old. The average age of John, Mary, and Tanya is 105/",
      "input_tokens": 26,
      "output_tokens": 28,
      "latency_ms": 585.0001875835908,
      "finish_reason": "stop",
      "mock": true
    },
    {
      "turn_index": 6,
      "tutor_turn": "(generic)fab",
      "learner_turn": "Thank you!",
      "input_tokens": 10,
      "output_tokens": 2,
      "latency_ms": 643.558065100513,
      "finish_reason": "stop",
      "mock": true
    },
    {
      "turn_index": 7,
      "tutor_turn": "Now try this similar problem on your own without any hints. Show your reasoning step by step:\n\nJohn is twice as old as Mary and half as old as Tonya. If Tanya is 89.2, what is their average age?",
      "learner_turn": "I think it's something like that. Let me try.",
      "input_tokens": 48,
      "output_tokens": 9,
      "latency_ms": 778.2495806617733,
      "finish_reason": "stop",
      "mock": true
    }
  ],
  "mock": true
}